{
  "$schema": "https://docs.renovatebot.com/renovate-schema.json",
  "description": "Default configuration for oriflame",
  "extends": [
    ":ignoreModulesAndTests",
    ":semanticCommitScopeDisabled"
  ],
  "updateLockFiles": true,
  "azureAutoComplete": true,
  "commitMessageTopic": "dependency {{depName}}",
  "commitMessage": "{{{commitMessagePrefix}}} {{{commitMessageAction}}} {{{commitMessageTopic}}}{{{commitMessageSuffix}}}",
  "commitMessageAction": "Update",
  "commitMessageSuffix": ".",
  "rangeStrategy": "bump",
  "enabledManagers": [
    "npm"
  ]
}